RIL/__init__.py
RIL/_core.py
RIL/bootstrap/__init__.py
RIL/bootstrap/component.py
RIL/bootstrap/component.pyi
RIL/fontawesome/__init__.py
RIL/fontawesome/component.py
RIL/fontawesome/component.pyi
RIL/lucide/__init__.py
RIL/lucide/component.py
RIL/material/__init__.py
RIL/material/component.py
RIL/material/component.pyi
RIL/octicons/__init__.py
RIL/octicons/component.py
RIL/octicons/component.pyi
RIL/phosphor/__init__.py
RIL/phosphor/component.py
RIL/phosphor/component.pyi
RIL/plugins/__init__.py
RIL/plugins/svgr.py
RIL/settings.py
RIL/simple/SimpleIcon.jsx
RIL/simple/__init__.py
RIL/simple/component.py
RIL/simple/component.pyi
RIL/templates/.npmrc.jinja
RIL/templates/__init__.py
RIL/templates/vite.config.js
RIL/utils.py
reflex_icon_library-2.0.1.dist-info/METADATA
reflex_icon_library-2.0.1.dist-info/WHEEL
reflex_icon_library-2.0.1.dist-info/entry_points.txt
reflex_icon_library-2.0.1.dist-info/licenses/LICENSE.md
reflex_icon_library-2.0.1.dist-info/RECORD
